openai_structured/__init__.py
openai_structured/buffer.py
openai_structured/client.py
openai_structured/config/models.yml
openai_structured/config/parameter_constraints.yml
openai_structured/errors.py
openai_structured/examples/__init__.py
openai_structured/examples/schemas/__init__.py
openai_structured/logging.py
openai_structured/model_registry.py
openai_structured/model_version.py
openai_structured/py.typed
openai_structured/scripts/update_registry.py
openai_structured/testing/__init__.py
openai_structured/testing/templates/temp_test_constraints.yml
openai_structured/testing/templates/temp_test_models.yml
openai_structured/testing/templates/test_constraints.yml
openai_structured/testing/templates/test_models.yml
openai_structured-3.0.0.dist-info/LICENSE
openai_structured-3.0.0.dist-info/METADATA
openai_structured-3.0.0.dist-info/WHEEL
openai_structured-3.0.0.dist-info/entry_points.txt
openai_structured-3.0.0.dist-info/RECORD
